[{"_id": 1999, "min": 18, "max": 65, "avg": 39.26923076923077}, {"_id": 2000, "min": 19, "max": 65, "avg": 38.266666666666666}, {"_id": 2001, "min": 18, "max": 65, "avg": 40.65625}, {"_id": 2002, "min": 18, "max": 65, "avg": 40.40425531914894}, {"_id": 2003, "min": 18, "max": 64, "avg": 43.5}, {"_id": 2004, "min": 18, "max": 65, "avg": 43.093023255813954}, {"_id": 2005, "min": 18, "max": 65, "avg": 39.394366197183096}, {"_id": 2006, "min": 18, "max": 65, "avg": 44.85}, {"_id": 2007, "min": 21, "max": 65, "avg": 44.76315789473684}, {"_id": 2008, "min": 19, "max": 65, "avg": 39.21153846153846}, {"_id": 2009, "min": 18, "max": 65, "avg": 43.67272727272727}, {"_id": 2010, "min": 18, "max": 65, "avg": 36.241379310344826}, {"_id": 2011, "min": 18, "max": 65, "avg": 42.78260869565217}, {"_id": 2012, "min": 19, "max": 65, "avg": 39.26315789473684}, {"_id": 2013, "min": 20, "max": 65, "avg": 41.98039215686274}, {"_id": 2014, "min": 20, "max": 65, "avg": 44.0625}, {"_id": 2015, "min": 19, "max": 65, "avg": 45.72727272727273}, {"_id": 2016, "min": 18, "max": 65, "avg": 45.47222222222222}, {"_id": 2017, "min": 18, "max": 63, "avg": 42.416666666666664}, {"_id": 2018, "min": 18, "max": 65, "avg": 43.714285714285715}, {"_id": 2019, "min": 18, "max": 65, "avg": 42.5625}, {"_id": 2020, "min": 18, "max": 63, "avg": 42.5}, {"_id": 2021, "min": 20, "max": 65, "avg": 42.78}, {"_id": 2022, "min": 18, "max": 64, "avg": 40.11864406779661}]